amzn_nova_prompt_optimizer/__init__.py
amzn_nova_prompt_optimizer/__version__.py
amzn_nova_prompt_optimizer/py.typed
amzn_nova_prompt_optimizer/core/__init__.py
amzn_nova_prompt_optimizer/core/evaluation/__init__.py
amzn_nova_prompt_optimizer/core/inference/__init__.py
amzn_nova_prompt_optimizer/core/inference/adapter.py
amzn_nova_prompt_optimizer/core/inference/bedrock_converse.py
amzn_nova_prompt_optimizer/core/inference/inference_constants.py
amzn_nova_prompt_optimizer/core/input_adapters/__init__.py
amzn_nova_prompt_optimizer/core/input_adapters/dataset_adapter.py
amzn_nova_prompt_optimizer/core/input_adapters/metric_adapter.py
amzn_nova_prompt_optimizer/core/input_adapters/prompt_adapter.py
amzn_nova_prompt_optimizer/core/optimizers/__init__.py
amzn_nova_prompt_optimizer/core/optimizers/adapter.py
amzn_nova_prompt_optimizer/core/optimizers/miprov2/__init__.py
amzn_nova_prompt_optimizer/core/optimizers/miprov2/miprov2_optimizer.py
amzn_nova_prompt_optimizer/core/optimizers/miprov2/custom_adapters/custom_chat_adapter.py
amzn_nova_prompt_optimizer/core/optimizers/miprov2/custom_lm/rate_limited_lm.py
amzn_nova_prompt_optimizer/core/optimizers/nova_meta_prompter/__init__.py
amzn_nova_prompt_optimizer/core/optimizers/nova_meta_prompter/nova_mp_optimizer.py
amzn_nova_prompt_optimizer/core/optimizers/nova_meta_prompter/nova_prompt_template.py
amzn_nova_prompt_optimizer/core/optimizers/nova_prompt_optimizer/__init__.py
amzn_nova_prompt_optimizer/core/optimizers/nova_prompt_optimizer/nova_grounded_proposer.py
amzn_nova_prompt_optimizer/core/optimizers/nova_prompt_optimizer/nova_prompt_optimizer.py
amzn_nova_prompt_optimizer/util/__init__.py
amzn_nova_prompt_optimizer/util/logging_utils.py
amzn_nova_prompt_optimizer/util/rate_limiter.py
nova_prompt_optimizer-1.0.53.dist-info/licenses/LICENSE
nova_prompt_optimizer-1.0.53.dist-info/licenses/NOTICE
nova_prompt_optimizer-1.0.53.dist-info/METADATA
nova_prompt_optimizer-1.0.53.dist-info/WHEEL
nova_prompt_optimizer-1.0.53.dist-info/top_level.txt
nova_prompt_optimizer-1.0.53.dist-info/RECORD
