Metadata-Version: 2.4
Name: nova-prompt-optimizer
Version: 1.0.53
Summary: A Python SDK for optimizing prompts for Nova.
Author-email: Amazon <nova-prompt-optimizer@amazon.com>
License-Expression: Apache-2.0
Requires-Python: >=3.11
License-File: LICENSE
License-File: NOTICE
Requires-Dist: jinja2
Requires-Dist: boto3
Requires-Dist: botocore
Requires-Dist: boto3-stubs
Requires-Dist: dspy==2.6.27
Requires-Dist: numpy==2.3.2
Requires-Dist: virtualenv==20.31.2
Requires-Dist: urllib3==2.5.0
Requires-Dist: setuptools==80.9.0
Requires-Dist: h11==0.16.0
Provides-Extra: dev
Requires-Dist: build; extra == "dev"
Requires-Dist: setuptools; extra == "dev"
Requires-Dist: twine; extra == "dev"
Requires-Dist: wheel; extra == "dev"
Dynamic: license-file
